diffdart/dart_torch_loss_fn.py
diffdart/dart_map_pos.py
diffdart/dart_trajectory_trainer.py
diffdart/__init__.py
diffdart/dart_world_space_transforms.py
diffdart/dart_gui_server.py
diffdart/dart_layer.py
diffdart/web_gui/index.html
diffdart/web_gui/bundle.js
diffdart_libs/__init__.py
diffdart_libs/_diffdart.so
diffdart_libs/.dylibs/libicui18n.68.2.dylib
diffdart_libs/.dylibs/liburdfdom_world.dylib
diffdart_libs/.dylibs/liburdfdom_model_state.dylib
diffdart_libs/.dylibs/libboost_filesystem-mt.dylib
diffdart_libs/.dylibs/libassimp.5.dylib
diffdart_libs/.dylibs/libccd.2.dylib
diffdart_libs/.dylibs/libcoinmumps.2.dylib
diffdart_libs/.dylibs/libipopt.3.dylib
diffdart_libs/.dylibs/liburdfdom_model.1.0.dylib
diffdart_libs/.dylibs/libconsole_bridge.1.0.dylib
diffdart_libs/.dylibs/libboost_system-mt.dylib
diffdart_libs/.dylibs/libgfortran.5.dylib
diffdart_libs/.dylibs/libconsole_bridge.dylib
diffdart_libs/.dylibs/libicuuc.68.2.dylib
diffdart_libs/.dylibs/libicudata.68.2.dylib
diffdart_libs/.dylibs/libquadmath.0.dylib
diffdart_libs/.dylibs/liburdfdom_sensor.dylib
diffdart_libs/.dylibs/libboost_regex-mt.dylib
diffdart_libs/.dylibs/libz.1.dylib
diffdart_libs/.dylibs/libgcc_s.1.dylib
diffdart_libs/.dylibs/liburdfdom_model.dylib
diffdart_libs/.dylibs/libtinyxml.2.6.2.dylib
diffdart_libs/.dylibs/libtinyxml2.8.dylib
diffdart-0.4.0.dist-info/RECORD
diffdart-0.4.0.dist-info/LICENSE
diffdart-0.4.0.dist-info/WHEEL
diffdart-0.4.0.dist-info/top_level.txt
diffdart-0.4.0.dist-info/METADATA
