Metadata-Version: 2.1
Name: diffdart
Version: 0.4.0
Summary: A differentiable fully featured physics engine
Home-page: UNKNOWN
Author: Keenon Werling
Author-email: keenonwerling@gmail.com
License: MIT
Platform: UNKNOWN
Requires-Dist: torch
Requires-Dist: numpy
